portgate/__init__.py
portgate/cli.py
portgate/core.py
portgate/exceptions.py
portgate-1.0.1.dist-info/LICENSE
portgate-1.0.1.dist-info/METADATA
portgate-1.0.1.dist-info/WHEEL
portgate-1.0.1.dist-info/entry_points.txt
portgate-1.0.1.dist-info/top_level.txt
portgate-1.0.1.dist-info/RECORD
