Metadata-Version: 2.1
Name: portgate
Version: 1.0.1
Summary: A command-line utility to manage port mappings on your local router using UPnP/NAT-PMP
Author-email: Sarper AVCI <sarperavci20@gmail.com>
License: MIT
Project-URL: Homepage, https://github.com/sarperavci/PortGate
Project-URL: Repository, https://github.com/sarperavci/PortGate
Project-URL: Documentation, https://github.com/sarperavci/PortGate#readme
Project-URL: Issues, https://github.com/sarperavci/PortGate/issues
Classifier: Development Status :: 4 - Beta
Classifier: Intended Audience :: Developers
Classifier: License :: OSI Approved :: MIT License
Classifier: Operating System :: OS Independent
Classifier: Programming Language :: Python :: 3
Classifier: Programming Language :: Python :: 3.8
Classifier: Programming Language :: Python :: 3.9
Classifier: Programming Language :: Python :: 3.10
Classifier: Programming Language :: Python :: 3.11
Classifier: Topic :: System :: Networking :: Firewalls
Classifier: Topic :: Utilities
Classifier: Topic :: Internet :: WWW/HTTP
Classifier: Topic :: System :: Systems Administration
Requires-Python: >=3.8
License-File: LICENSE
Requires-Dist: miniupnpc>=2.3.0
